{
  "$schema": "https://raw.githubusercontent.com/stryker-mutator/stryker-js/master/packages/core/schema/stryker-schema.json",
  "mutate": [
    "src/**/*.ts",
    "samples/app.ts",
    "!src/report/**",
    "!tests/**"
  ],
  "testRunner": "jest",
  "jest": { "configFile": "jest.config.cjs" },
  "coverageAnalysis": "perTest",
  "checkers": ["typescript"],
  "tsconfigFile": "tsconfig.json",
  "thresholds": { "high": 80, "low": 60, "break": 50 },
  "ignoreStatic": true,
  "reporters": ["clear-text", "progress", "html", "json"],
  "jsonReporter": { "fileName": "reports/mutation/mutation-report.json" },
  "htmlReporter": { "fileName": "reports/mutation/mutation.html" },
  "timeoutMS": 60000
}
